{
"units":[
{"id":101, "body":"101", "base":"",	"overlay":"",	"summon":"base",   "y":-12,	"bullet":"black-s",		  "bulletFX":"",	"smoke":"base",	"flame":"base",	"hit":"hit-",		  "die":"blood-", "p":[275,190,203,202,160,248,166,312,235,351], "sd":0, "hitShake":0.0, "dieShake":0.0,  "summonSFX":["101-summon"], "hitSFX":[],    "dieSFX":[],    "attackSFX":["101-attack"]},
{"id":102, "body":"102", "base":"",	"overlay":"",	"summon":"base",   "y":-12,	"bullet":"",      		  "bulletFX":"",	"smoke":"",	    "flame":"",   	"hit":"hit-",		  "die":"blood-", "p":[256,232,165,237,128,315,171,395,265,427], "sd":1, "hitShake":0.0, "dieShake":0.0,	"summonSFX":["102-summon"], "hitSFX":[],    "dieSFX":[],    "attackSFX":["102-attack"]},
{"id":103, "body":"103", "base":"",	"overlay":"",	"summon":"",       "y":-32,	"bullet":"",				    "bulletFX":"",	"smoke":"",		  "flame":"",		  "hit":"ps-melee",	"die":"blood-", "p":[232,182,153,217,125,289,177,359,285,377], "sd":0, "hitShake":0.0, "dieShake":0.0,	"summonSFX":["103-summon"], "hitSFX":[],    "dieSFX":[],    "attackSFX":["103-attack-1", "103-attack-2", "103-attack-3", "103-attack-4", "103-attack-5"]},
{"id":104, "body":"104", "base":"",	"overlay":"",	"summon":"base",   "y":-12,	"bullet":"spell",   	  "bulletFX":"",	"smoke":"",	    "flame":"",	    "hit":"",			    "die":"blood-", "p":[275,169,212,182,173,224,175,281,236,318], "sd":1, "hitShake":0.0, "dieShake":0.0,	"summonSFX":["101-summon"], "hitSFX":[],    "dieSFX":[],    "attackSFX":["104-attack"]},
{"id":105, "body":"105", "base":"",	"overlay":"",	"summon":"base",   "y":-12,	"bullet":"",				    "bulletFX":"",	"smoke":"",		  "flame":"",		  "hit":"ps-melee",	"die":"blood-", "p":[232,182,153,217,125,289,177,359,285,377], "sd":1, "hitShake":0.0, "dieShake":0.0,	"summonSFX":["105-summon"], "hitSFX":[],    "dieSFX":[],    "attackSFX":["105-attack"]},
{"id":106, "body":"106", "base":"",	"overlay":"",	"summon":"base",   "y":-12,	"bullet":"grenade",		  "bulletFX":"",	"smoke":"",		  "flame":"",		  "hit":"explode-",	"die":"blood-", "p":[278,235,250,227,201,259,201,298,236,318], "sd":0, "hitShake":0.3, "dieShake":0.0,	"summonSFX":["106-summon"], "hitSFX":["e"], "dieSFX":[],    "attackSFX":["106-attack"]},
{"id":107, "body":"107", "base":"",	"overlay":"",	"summon":"base",   "y":-2,  "bullet":"",				    "bulletFX":"",	"smoke":"",		  "flame":"",		  "hit":"explode-",	"die":"", 		  "p":[232,182,153,217,125,289,177,359,285,377], "sd":0, "hitShake":0.0, "dieShake":1.0,	"summonSFX":["107-summon"], "hitSFX":[],    "dieSFX":[],    "attackSFX":["107-attack"]},
{"id":108, "body":"108", "base":"",	"overlay":"",	"summon":"base",   "y":-3,  "bullet":"black-s",		  "bulletFX":"",	"smoke":"",		  "flame":"",		  "hit":"",			    "die":"blood-", "p":[262,256,224,264,205,296,214,334,246,352], "sd":1, "hitShake":0.0, "dieShake":0.0,	"summonSFX":["108-summon"], "hitSFX":[],    "dieSFX":[],    "attackSFX":["108-attack"]},
{"id":109, "body":"109", "base":"",	"overlay":"",	"summon":"base",   "y":-12,	"bullet":"heal",			  "bulletFX":"",	"smoke":"",		  "flame":"",		  "hit":"hit-",		  "die":"blood-", "p":[259,197,192,220,153,268,180,331,253,353], "sd":0, "hitShake":0.0, "dieShake":0.0,	"summonSFX":["109-summon"], "hitSFX":[],    "dieSFX":[],    "attackSFX":["109-attack"]},
{"id":110, "body":"110", "base":"",	"overlay":"",	"summon":"base",   "y":-12,	"bullet":"black-s",		  "bulletFX":"",	"smoke":"",		  "flame":"",		  "hit":"hit-",		  "die":"blood-", "p":[265,201,204,214,168,257,180,313,245,346], "sd":0, "hitShake":0.0, "dieShake":0.0,	"summonSFX":["103-summon"], "hitSFX":[],    "dieSFX":[],    "attackSFX":["110-attack"]},
{"id":111, "body":"111", "base":"",	"overlay":"",	"summon":"base",   "y":-12,	"bullet":"ps-splash",	  "bulletFX":"",	"smoke":"base",	"flame":"base",	"hit":"",			    "die":"blood-", "p":[232,182,153,217,125,289,177,359,285,377], "sd":0, "hitShake":0.0, "dieShake":0.0,	"summonSFX":["111-summon"], "hitSFX":[],    "dieSFX":[],    "attackSFX":["111-attack"]},
{"id":112, "body":"112", "base":"",	"overlay":"",	"summon":"base",   "y":-12,	"bullet":"",				    "bulletFX":"",	"smoke":"",		  "flame":"",		  "hit":"hit-",		  "die":"blood-", "p":[232,182,153,217,125,289,177,359,285,377], "sd":1, "hitShake":0.0, "dieShake":0.0,	"summonSFX":["113-summon"], "hitSFX":[],    "dieSFX":[],    "attackSFX":["113-attack"]},
{"id":113, "body":"113", "base":"",	"overlay":"",	"summon":"base",   "y":-12,	"bullet":"",				    "bulletFX":"",	"smoke":"",		  "flame":"",		  "hit":"hit-",		  "die":"blood-", "p":[232,182,153,217,125,289,177,359,285,377], "sd":0, "hitShake":0.0, "dieShake":0.0,	"summonSFX":["113-summon"], "hitSFX":[],    "dieSFX":[],    "attackSFX":["113-attack"]},
{"id":114, "body":"114", "base":"",	"overlay":"",	"summon":"base",   "y":-12,	"bullet":"",				    "bulletFX":"",	"smoke":"",		  "flame":"",		  "hit":"ps-melee",	"die":"blood-", "p":[232,182,153,217,125,289,177,359,285,377], "sd":0, "hitShake":0.0, "dieShake":0.0,	"summonSFX":["103-summon"], "hitSFX":[],    "dieSFX":[],    "attackSFX":["103-attack-1", "103-attack-2", "103-attack-3", "103-attack-4", "103-attack-5"]},
{"id":115, "body":"115", "base":"",	"overlay":"",	"summon":"base",   "y":-12,	"bullet":"",				    "bulletFX":"",	"smoke":"",		  "flame":"",		  "hit":"ps-melee",	"die":"blood-", "p":[232,182,153,217,125,289,177,359,285,377], "sd":0, "hitShake":0.0, "dieShake":0.0,	"summonSFX":["105-summon"], "hitSFX":[],    "dieSFX":[],    "attackSFX":["105-attack"]},
{"id":116, "body":"116", "base":"b","overlay":"o","summon":"base",   "y":-12,	"bullet":"grenade",		  "bulletFX":"",	"smoke":"",		  "flame":"",		  "hit":"explode-",	"die":"wood-",  "p":[232,182,153,217,125,289,177,359,285,377], "sd":0, "hitShake":0.3, "dieShake":0.0,	"summonSFX":["106-summon"], "hitSFX":["e"], "dieSFX":[],    "attackSFX":["106-attack"]},
{"id":117, "body":"117", "base":"",	"overlay":"",	"summon":"",       "y":-12,	"bullet":"",				    "bulletFX":"",	"smoke":"",		  "flame":"",		  "hit":"ps-melee",	"die":"blood-", "p":[232,182,153,217,125,289,177,359,285,377], "sd":1, "hitShake":0.0, "dieShake":0.0,	"summonSFX":["117-summon"], "hitSFX":[],    "dieSFX":[],    "attackSFX":["117-attack"]},
{"id":118, "body":"118", "base":"",	"overlay":"",	"summon":"",       "y":-12,	"bullet":"grenade",	    "bulletFX":"",	"smoke":"",		  "flame":"",		  "hit":"explode",	"die":"",       "p":[232,182,153,217,125,289,177,359,285,377], "sd":1, "hitShake":0.0, "dieShake":0.5,	"summonSFX":["107-summon"], "hitSFX":[],    "dieSFX":[],    "attackSFX":["106-attack"]},
{"id":119, "body":"119", "base":"",	"overlay":"",	"summon":"base",   "y":-12,	"bullet":"black-l",		  "bulletFX":"",	"smoke":"base",	"flame":"base",	"hit":"hit-",		  "die":"wood-",  "p":[256,248,221,264,207,295,217,333,256,350], "sd":1, "hitShake":0.0, "dieShake":0.0,	"summonSFX":["108-summon"], "hitSFX":[],    "dieSFX":[],    "attackSFX":["119-attack"]},
{"id":120, "body":"117", "base":"",	"overlay":"",	"summon":"",       "y":-12,	"bullet":"",				    "bulletFX":"",	"smoke":"",		  "flame":"",		  "hit":"ps-melee",	"die":"blood-", "p":[232,182,153,217,125,289,177,359,285,377], "sd":1, "hitShake":0.0, "dieShake":0.0,	"summonSFX":["117-summon"], "hitSFX":[],    "dieSFX":[],    "attackSFX":["117-attack"]},
{"id":121, "body":"103", "base":"",	"overlay":"",	"summon":"",       "y":-32,	"bullet":"",				    "bulletFX":"",	"smoke":"",		  "flame":"",		  "hit":"ps-melee",	"die":"blood-", "p":[232,182,153,217,125,289,177,359,285,377], "sd":0, "hitShake":0.0, "dieShake":0.0,	"summonSFX":["103-summon"], "hitSFX":[],    "dieSFX":[],    "attackSFX":["103-attack-1", "103-attack-2", "103-attack-3", "103-attack-4", "103-attack-5"]},

{"id":151, "body":"151", "base":"",	"overlay":"",	"summon":"base",   "y":-12,	"bullet":"bomb",		    "bulletFX":"",	"smoke":"",		  "flame":"",		  "hit":"explode-",	"die":"", 		  "p":[232,182,153,217,125,289,177,359,285,377], "sd":0, "hitShake":1.2, "dieShake":0.0,	"summonSFX":["151-summon"], "hitSFX":["e"], "dieSFX":[],    "attackSFX":["151-attack"]},
{"id":152, "body":"152", "base":"",	"overlay":"",	"summon":"base",   "y":-12,	"bullet":"arrow-hord",  "bulletFX":"",	"smoke":"",		  "flame":"",		  "hit":"arrows-",	"die":"",		    "p":[232,182,153,217,125,289,177,359,285,377], "sd":0, "hitShake":0.0, "dieShake":0.0,	"summonSFX":["152-summon"], "hitSFX":[],    "dieSFX":[],    "attackSFX":["152-attack"]},
{"id":153, "body":"153", "base":"",	"overlay":"",	"summon":"base",   "y":-12,	"bullet":"",				    "bulletFX":"",	"smoke":"",		  "flame":"",		  "hit":"freeze-",	"die":"",		    "p":[232,182,153,217,125,289,177,359,285,377], "sd":0, "hitShake":0.0, "dieShake":0.0,	"summonSFX":["153-summon"], "hitSFX":["e"], "dieSFX":[],    "attackSFX":["153-attack"]},

{"id":201, "body":"201", "base":"b","overlay":"",	"summon":"base",	 "y":-12, "bullet":"black-s",		  "bulletFX":"",	"smoke":"base",	"flame":"base",	"hit":"hit-",		  "die":"u-car-", "p":[230,175,148,212,120,286,171,354,287,375], "sd":0, "hitShake":0.0, "dieShake":1.5,	"summonSFX":[],				      "hitSFX":[],    "dieSFX":["e"], "attackSFX":["201-attack"]},
{"id":202, "body":"202", "base":"",	"overlay":"",	"summon":"base",   "y":-12,	"bullet":"",      		  "bulletFX":"",	"smoke":"",	    "flame":"",	    "hit":"",	    	  "die":"coins-", "p":[],                                        "sd":0, "hitShake":0.0, "dieShake":1.5,	"summonSFX":[],             "hitSFX":[],    "dieSFX":["e"], "attackSFX":[]},

{"id":221, "body":"221", "base":"",	"overlay":"",	"summon":"base",	 "y":-12, "bullet":"",				    "bulletFX":"",	"smoke":"",		  "flame":"",		  "hit":"",			    "die":"blood-", "p":[232,182,153,217,125,289,177,359,285,377], "sd":0, "hitShake":0.0, "dieShake":1.0,	"summonSFX":[],				      "hitSFX":[],    "dieSFX":[],    "attackSFX":["221-attack"]},
{"id":222, "body":"222", "base":"",	"overlay":"",	"summon":"base",	 "y":-5,  "bullet":"black-s",		  "bulletFX":"",	"smoke":"base",	"flame":"base",	"hit":"hit-",		  "die":"blood-", "p":[235,176,160,209,133,275,179,341,281,361], "sd":0, "hitShake":0.0, "dieShake":1.0,	"summonSFX":[],				      "hitSFX":[],    "dieSFX":[],    "attackSFX":["222-attack"]},
{"id":223, "body":"223", "base":"",	"overlay":"",	"summon":"base",	 "y":-12, "bullet":"",		        "bulletFX":"",	"smoke":"",	    "flame":"",	    "hit":"",		      "die":"blood-", "p":[232,182,153,217,125,289,177,359,285,377], "sd":0, "hitShake":0.0, "dieShake":1.0,	"summonSFX":[],				      "hitSFX":[],    "dieSFX":[],    "attackSFX":["103-attack-1", "103-attack-2", "103-attack-3", "103-attack-4", "103-attack-5"]},
{"id":224, "body":"119", "base":"",	"overlay":"",	"summon":"base",   "y":-12,	"bullet":"black-l",		  "bulletFX":"",	"smoke":"base",	"flame":"base",	"hit":"hit-",		  "die":"wood-",  "p":[256,248,221,264,207,295,217,333,256,350], "sd":1, "hitShake":0.0, "dieShake":0.0,	"summonSFX":["108-summon"], "hitSFX":[],    "dieSFX":[],    "attackSFX":["119-attack"]},

{"id":241, "body":"",    "base":"", "overlay":"",	"summon":"base",   "y":-12,	"bullet":"",      		  "bulletFX":"",	"smoke":"",	    "flame":"",	    "hit":"",	    	  "die":"",       "p":[],                                        "sd":0, "hitShake":0.0, "dieShake":0.0,	"summonSFX":[],             "hitSFX":[],    "dieSFX":[],    "attackSFX":[]}
]
}